lastfmapi.py
setup.py
lastfmapi.egg-info/PKG-INFO
lastfmapi.egg-info/SOURCES.txt
lastfmapi.egg-info/dependency_links.txt
lastfmapi.egg-info/top_level.txt