Metadata-Version: 1.0
Name: lastfmapi
Version: 0.1
Summary: A thin wrapper for accessing the Last.fm API
Home-page: https://github.com/rockstar/lastfmapi
Author: Paul Hummer
Author-email: paul@eventuallyanyway.com
License: http://www.opensource.org/licenses/mit-license.php
Keywords: last.fm api
Platform: UNKNOWN
